shouterlog/__init__.py
shouterlog/setup.py
shouterlog/shouterlog.py
shouterlog/.paa.tracking/.paa.config
shouterlog/.paa.tracking/.paa.version
shouterlog/.paa.tracking/lsts_package_versions.yml
shouterlog/.paa.tracking/notebook.ipynb
shouterlog/.paa.tracking/package_licenses.json
shouterlog/.paa.tracking/package_mapping.json
shouterlog/.paa.tracking/release_notes.md
shouterlog/.paa.tracking/version_logs.csv
shouterlog/.paa.tracking/python_modules/shouterlog.py
shouterlog/.paa.tracking/python_modules/components/shouterlog/asyncio_patch.py
shouterlog/.paa.tracking/python_modules/components/shouterlog/log_plotter.py
shouterlog/mkdocs/mkdocs.yml
shouterlog/mkdocs/docs/description.md
shouterlog/mkdocs/docs/index.md
shouterlog/mkdocs/docs/release-notes.md
shouterlog/mkdocs/docs/css/extra.css
shouterlog/mkdocs/docs/images/shouterlog_cell22_out0.png
shouterlog/mkdocs/site/404.html
shouterlog/mkdocs/site/index.html
shouterlog/mkdocs/site/sitemap.xml
shouterlog/mkdocs/site/sitemap.xml.gz
shouterlog/mkdocs/site/assets/images/favicon.png
shouterlog/mkdocs/site/assets/javascripts/bundle.fe8b6f2b.min.js
shouterlog/mkdocs/site/assets/javascripts/bundle.fe8b6f2b.min.js.map
shouterlog/mkdocs/site/assets/javascripts/lunr/tinyseg.js
shouterlog/mkdocs/site/assets/javascripts/lunr/wordcut.js
shouterlog/mkdocs/site/assets/javascripts/lunr/min/lunr.ar.min.js
shouterlog/mkdocs/site/assets/javascripts/lunr/min/lunr.da.min.js
shouterlog/mkdocs/site/assets/javascripts/lunr/min/lunr.de.min.js
shouterlog/mkdocs/site/assets/javascripts/lunr/min/lunr.du.min.js
shouterlog/mkdocs/site/assets/javascripts/lunr/min/lunr.el.min.js
shouterlog/mkdocs/site/assets/javascripts/lunr/min/lunr.es.min.js
shouterlog/mkdocs/site/assets/javascripts/lunr/min/lunr.fi.min.js
shouterlog/mkdocs/site/assets/javascripts/lunr/min/lunr.fr.min.js
shouterlog/mkdocs/site/assets/javascripts/lunr/min/lunr.he.min.js
shouterlog/mkdocs/site/assets/javascripts/lunr/min/lunr.hi.min.js
shouterlog-0.3.0.dist-info/licenses/LICENSE
shouterlog-0.3.0.dist-info/METADATA
shouterlog-0.3.0.dist-info/WHEEL
shouterlog-0.3.0.dist-info/top_level.txt
shouterlog-0.3.0.dist-info/RECORD
