Metadata-Version: 2.4
Name: shouterlog
Version: 0.3.0
Summary: A custom logging tool that expands normal logger with additional formatting and debug capabilities.
Author: Kyrylo Mordan
Author-email: parachute.repo@gmail.com
License: mit
Keywords: python,logging,debug tool,aa-paa-tool
Classifier: Development Status :: 3 - Alpha
Classifier: Intended Audience :: Developers
Classifier: Intended Audience :: Science/Research
Classifier: Programming Language :: Python :: 3
Classifier: Programming Language :: Python :: 3.9
Classifier: Programming Language :: Python :: 3.10
Classifier: Programming Language :: Python :: 3.11
Classifier: Programming Language :: Python :: 3.12
Classifier: License :: OSI Approved :: MIT License
Classifier: Topic :: Scientific/Engineering
License-File: LICENSE
Requires-Dist: matplotlib
Requires-Dist: dill>=0.3.7
Requires-Dist: attrs
Requires-Dist: attrsx
Dynamic: author
Dynamic: author-email
Dynamic: classifier
Dynamic: description
Dynamic: description-content-type
Dynamic: keywords
Dynamic: license
Dynamic: license-file
Dynamic: requires-dist
Dynamic: summary
